odoo10_addon_project_task_report-10.0.1.0.0-py2.7-nspkg.pth
odoo/addons/project_task_report/README.rst
odoo/addons/project_task_report/__init__.py
odoo/addons/project_task_report/__manifest__.py
odoo/addons/project_task_report/static/description/icon.png
odoo/addons/project_task_report/views/project_task_chatter_report.xml
odoo/addons/project_task_report/views/project_task_report.xml
odoo10_addon_project_task_report-10.0.1.0.0.dist-info/DESCRIPTION.rst
odoo10_addon_project_task_report-10.0.1.0.0.dist-info/METADATA
odoo10_addon_project_task_report-10.0.1.0.0.dist-info/RECORD
odoo10_addon_project_task_report-10.0.1.0.0.dist-info/WHEEL
odoo10_addon_project_task_report-10.0.1.0.0.dist-info/metadata.json
odoo10_addon_project_task_report-10.0.1.0.0.dist-info/namespace_packages.txt
odoo10_addon_project_task_report-10.0.1.0.0.dist-info/top_level.txt
